multiping/__init__.py
multiping-1.1.0.dist-info/DESCRIPTION.rst
multiping-1.1.0.dist-info/METADATA
multiping-1.1.0.dist-info/RECORD
multiping-1.1.0.dist-info/WHEEL
multiping-1.1.0.dist-info/metadata.json
multiping-1.1.0.dist-info/top_level.txt
