Metadata-Version: 1.1
Name: multiping
Version: 1.1.0
Summary: Pure python library to send and receive ICMPecho request (ping) to monitor IP addresses
Home-page: http://github.com/romana/multi-ping/
Author: Juergen Brendel
Author-email: jbrendel@romana.io
License: Apache Software License
Platform: UNKNOWN
Classifier: Programming Language :: Python
Classifier: Natural Language :: English
Classifier: Environment :: Plugins
Classifier: Intended Audience :: Developers
Classifier: License :: OSI Approved :: Apache Software License
Classifier: Operating System :: POSIX :: Linux
Classifier: Topic :: System :: Monitoring
Classifier: Topic :: Software Development :: Libraries :: Python Modules
